jordan_test_package_repo/__init__.py
jordan_test_package_repo/_version.py
jordan_test_package_repo/module1_lets_get_it.py
jordan_test_package_repo/py.typed
jordan_test_package_repo/tests/__init__.py
jordan_test_package_repo/tests/test_jordan_test_package_repo.py
jordan_test_package_repo-0.0.2.dist-info/LICENSE
jordan_test_package_repo-0.0.2.dist-info/METADATA
jordan_test_package_repo-0.0.2.dist-info/WHEEL
jordan_test_package_repo-0.0.2.dist-info/top_level.txt
jordan_test_package_repo-0.0.2.dist-info/RECORD
