Metadata-Version: 2.1
Name: jordan-test-package-repo
Version: 0.0.2
Summary: Just doing a little testy test
Author-email: Jordan Burns <jordanpburns13@gmail.com>
License: LGPLv3
Classifier: License :: OSI Approved :: GNU Lesser General Public License v3 or later (LGPLv3+)
Classifier: Programming Language :: Python :: 3
Requires-Python: >=3.8
License-File: LICENSE
Provides-Extra: test
Requires-Dist: pytest (>=6.1.2) ; extra == 'test'
Requires-Dist: pytest-runner ; extra == 'test'
